RepTate/CL.py
RepTate/MatDB.py
RepTate/RepTate.py
RepTate/UV.py
RepTate/__init__.py
RepTate/__main__.py
RepTate/_version.py
RepTate/applications/ApplicationCreep.py
RepTate/applications/ApplicationCrystal.py
RepTate/applications/ApplicationDielectric.py
RepTate/applications/ApplicationGt.py
RepTate/applications/ApplicationLAOS.py
RepTate/applications/ApplicationLVE.py
RepTate/applications/ApplicationMWD.py
RepTate/applications/ApplicationNLVE.py
RepTate/applications/ApplicationReact.py
RepTate/applications/ApplicationSANS.py
RepTate/applications/ApplicationSANS_JR_BACK.py
RepTate/applications/ApplicationTTS.py
RepTate/applications/ApplicationTTSFactors.py
RepTate/applications/ApplicationTemplate.py
RepTate/applications/ApplicationUniversalViewer.py
RepTate/applications/__init__.py
RepTate/applications/application_frs.py
RepTate/core/Application.py
RepTate/core/ApplicationManager.py
RepTate/core/CmdBase.py
RepTate/core/DataSet.py
RepTate/core/DataTable.py
RepTate/core/DraggableArtists.py
RepTate/core/File.py
RepTate/core/FileType.py
RepTate/core/MultiView.py
RepTate/core/Parameter.py
RepTate/core/Theory.py
RepTate/core/Tool.py
RepTate/core/View.py
RepTate/core/__init__.py
RepTate/core/mplcursors/__init__.py
RepTate/core/mplcursors/_mplcursors.py
RepTate/core/mplcursors/_pick_info.py
RepTate/core/mplcursors/_version.py
RepTate/gui/About.qrc
RepTate/gui/AboutDialog.ui
RepTate/gui/About_rc.py
RepTate/gui/DataSet.ui
RepTate/gui/DataSetWidget.py
RepTate/gui/DataSetWidgetItem.py
RepTate/gui/ImportExcelWindow.py
RepTate/gui/ImportFromPastedWindow.py
RepTate/gui/MainWindow.qrc
RepTate/gui/MainWindow_rc.py
RepTate/gui/MaterialsDatabase.ui
RepTate/gui/QAboutReptate.py
RepTate/gui/QApplicationManager.py
RepTate/gui/QApplicationWindow.py
RepTate/gui/QApplicationWindow.ui
RepTate/gui/QDataSet.py
RepTate/gui/QTheory.py
RepTate/gui/QTool.py
RepTate/gui/Reptate.qrc
RepTate/gui/ReptateMainWindow.ui
RepTate/gui/Reptate_rc.py
RepTate/gui/SplashScreen.py
RepTate-1.3.3.dist-info/LICENSE
RepTate-1.3.3.dist-info/METADATA
RepTate-1.3.3.dist-info/WHEEL
RepTate-1.3.3.dist-info/entry_points.txt
RepTate-1.3.3.dist-info/top_level.txt
RepTate-1.3.3.dist-info/RECORD
