Metadata-Version: 2.1
Name: RepTate
Version: 1.3.3
Summary: Rheology of Entangled Polymers: Toolkit for the Analysis of Theory and Experiment
Home-page: http://github.com/jorge-ramirez-upm/RepTate
Author: Jorge Ramirez, Victor Boudara
Author-email: reptate.rheology@gmail.com
License: GNU General Public License v3 or later (GPLv3+)
Classifier: License :: OSI Approved :: GNU General Public License v3 or later (GPLv3+)
Classifier: Programming Language :: Python :: 3
Classifier: Topic :: Scientific/Engineering
Classifier: Intended Audience :: Science/Research
Classifier: Operating System :: OS Independent
License-File: LICENSE
Requires-Dist: matplotlib >=3.2.1
Requires-Dist: openpyxl
Requires-Dist: PySide6
Requires-Dist: scipy
Requires-Dist: xlrd
Requires-Dist: psutil
